mb_netmgmt/__init__.py
mb_netmgmt/__main__.py
mb_netmgmt/netconf.py
mb_netmgmt/protocols.json
mb_netmgmt/snmp.py
mb_netmgmt/ssh_protocol.py
mb_netmgmt/telnet.py
mb_netmgmt-0.0.97.dist-info/licenses/COPYING
mb_netmgmt-0.0.97.dist-info/WHEEL
mb_netmgmt-0.0.97.dist-info/METADATA
mb_netmgmt-0.0.97.dist-info/RECORD
